bolsa/__init__.py
bolsa/backend.py
bolsa/connector.py
bolsa/constants.py
bolsa/http_client.py
bolsa/models.py
bolsa/responses.py
bolsa/contrib/__init__.py
bolsa/contrib/mixins/__init__.py
bolsa/contrib/mixins/singleton.py
bolsa/test/__init__.py
bolsa/test/test_constans.py
bolsa/test/test_models.py
bolsa-2.1.0.dist-info/METADATA
bolsa-2.1.0.dist-info/WHEEL
bolsa-2.1.0.dist-info/top_level.txt
bolsa-2.1.0.dist-info/RECORD
