Metadata-Version: 2.1
Name: bolsa
Version: 2.1.0
Summary: Biblioteca feita em python com o objetivo de facilitar o acesso a dados de seus investimentos na bolsa de valores(B3/CEI).
Home-page: https://github.com/gicornachini/bolsa
Author: Giovanni Cornachini
Author-email: giovannicornachini@gmail.com
License: UNKNOWN
Platform: UNKNOWN
Classifier: License :: OSI Approved :: Apache Software License
Classifier: Programming Language :: Python
Classifier: Programming Language :: Python :: 3.8
Classifier: Operating System :: MacOS :: MacOS X
Classifier: Operating System :: Microsoft :: Windows
Requires-Python: >=3.8.*
Requires-Dist: aiohttp (<4.0.0,>=3.6.2)
Requires-Dist: cchardet (>=2.1.6)
Requires-Dist: aiodns (>=2.0.0)
Requires-Dist: beautifulsoup4 (>=4.9.2)
